spip2/__init__.py
spip2/__main__.py
spip2-0.0.1.dist-info/LICENSE
spip2-0.0.1.dist-info/METADATA
spip2-0.0.1.dist-info/WHEEL
spip2-0.0.1.dist-info/entry_points.txt
spip2-0.0.1.dist-info/top_level.txt
spip2-0.0.1.dist-info/RECORD
