Metadata-Version: 2.1
Name: spip2
Version: 0.0.1
Summary: Wrapper of Python's pip
Home-page: https://github.com/sebbu2/spip2
Author: sebbu
Author-email: sebbu@yahoo.fr
License: MIT
Platform: UNKNOWN
Classifier: License :: OSI Approved :: MIT License
Classifier: Programming Language :: Python :: 3
Classifier: Programming Language :: Python :: 3.8
